ts3/__init__.py
ts3/commands.py
ts3/common.py
ts3/definitions.py
ts3/escape.py
ts3/filetransfer.py
ts3/qol_mixins.py
ts3/query.py
ts3/response.py
ts3/examples/__init__.py
ts3/examples/def_param.py
ts3/examples/endless_poke.py
ts3/examples/hello_bot.py
ts3/examples/mute_unmute.py
ts3/examples/viewer.py
ts3/examples/whirlpool.py
ts3query-2.0.1.dist-info/DESCRIPTION.rst
ts3query-2.0.1.dist-info/METADATA
ts3query-2.0.1.dist-info/RECORD
ts3query-2.0.1.dist-info/WHEEL
ts3query-2.0.1.dist-info/metadata.json
ts3query-2.0.1.dist-info/top_level.txt
