Metadata-Version: 2.0
Name: ts3query
Version: 2.0.1
Summary: TS3 Server&Client Query API
Home-page: https://gitlab.com/networkjanitor/py-ts3
Author: Xyoz Netsphere
Author-email: nanoowl@xyooz.net
License: License
Requires-Dist: blinker
Requires-Dist: sphinx
Requires-Dist: sphinx-rtd-theme
